README.rst
setup.cfg
setup.py
PtPclass/Studentclass.py
PtPclass/__init__.py
PtPclass.egg-info/PKG-INFO
PtPclass.egg-info/SOURCES.txt
PtPclass.egg-info/dependency_links.txt
PtPclass.egg-info/top_level.txt