Metadata-Version: 2.1
Name: PtPclass
Version: 0.0.7
Summary: package practice to learn python OOP by PtP
Home-page: https://github.com/Portuphet/PtPclass
Author: PtP
Author-email: t1hc0msupp0rt@gmail.com
License: MIT
Download-URL: https://github.com/Portuphet/PtPclass/archive/v_01.tar.gz
Keywords: pratice python,OOP,Portuphet
Platform: UNKNOWN
Classifier: Development Status :: 3 - Alpha
Classifier: Intended Audience :: Developers
Classifier: Topic :: Software Development :: Build Tools
Classifier: License :: OSI Approved :: MIT License
Classifier: Programming Language :: Python :: 3
Classifier: Programming Language :: Python :: 3.4
Classifier: Programming Language :: Python :: 3.5
Classifier: Programming Language :: Python :: 3.6
Classifier: Programming Language :: Python :: 3.7
Classifier: Programming Language :: Python :: 3.8
Classifier: Programming Language :: Python :: 3.9
